sienge_ecbiesek_mcp-3.1.3.dist-info/licenses/LICENSE
sienge_mcp/__init__.py
sienge_mcp/metadata.py
sienge_mcp/server.py
sienge_mcp/tools/__init__.py
sienge_mcp/tools/accounts_payable.py
sienge_mcp/tools/financial.py
sienge_mcp/tools/inventory.py
sienge_mcp/tools/kpi_cron.py
sienge_mcp/tools/kpi_maker.py
sienge_mcp/tools/master_data.py
sienge_mcp/tools/postgres_tools.py
sienge_mcp/tools/purchases.py
sienge_mcp/tools/supabase_tools.py
sienge_mcp/tools/utilities.py
sienge_mcp/utils/logger.py
sienge_ecbiesek_mcp-3.1.3.dist-info/METADATA
sienge_ecbiesek_mcp-3.1.3.dist-info/WHEEL
sienge_ecbiesek_mcp-3.1.3.dist-info/entry_points.txt
sienge_ecbiesek_mcp-3.1.3.dist-info/top_level.txt
sienge_ecbiesek_mcp-3.1.3.dist-info/RECORD
