Metadata-Version: 2.4
Name: sienge-ecbiesek-mcp
Version: 3.1.3
Summary: 🏗️ Model Context Protocol (MCP) server for Sienge API integration - Brazilian construction ERP system. Connect Claude AI to Sienge with 60+ powerful tools including smart validation, error parsing, complete invoice pipeline, and advanced caching for comprehensive business management.
Author-email: ECBIESEK <ti@ecbiesek.com>
License-Expression: MIT
Project-URL: Homepage, https://github.com/INOTECH-ecbiesek/Sienge-MCP
Project-URL: Documentation, https://github.com/INOTECH-ecbiesek/Sienge-MCP#readme
Project-URL: Repository, https://github.com/INOTECH-ecbiesek/Sienge-MCP.git
Project-URL: Issues, https://github.com/INOTECH-ecbiesek/Sienge-MCP/issues
Project-URL: Bug Reports, https://github.com/INOTECH-ecbiesek/Sienge-MCP/issues
Project-URL: Source Code, https://github.com/INOTECH-ecbiesek/Sienge-MCP
Project-URL: PyPI, https://pypi.org/project/sienge-ecbiesek-mcp/
Keywords: sienge,mcp,model-context-protocol,claude,api,construction,erp,brazil,ecbiesek,fastmcp,ai-integration
Classifier: Development Status :: 5 - Production/Stable
Classifier: Intended Audience :: Developers
Classifier: Intended Audience :: End Users/Desktop
Classifier: Operating System :: OS Independent
Classifier: Programming Language :: Python :: 3
Classifier: Programming Language :: Python :: 3.10
Classifier: Programming Language :: Python :: 3.11
Classifier: Programming Language :: Python :: 3.12
Classifier: Topic :: Software Development :: Libraries :: Python Modules
Classifier: Topic :: Office/Business :: Financial
Classifier: Topic :: Scientific/Engineering :: Interface Engine/Protocol Translator
Classifier: Topic :: Internet :: WWW/HTTP :: Dynamic Content
Classifier: Environment :: Console
Classifier: Framework :: FastAPI
Requires-Python: >=3.10
License-File: LICENSE
Requires-Dist: fastmcp>=2.12.3
Requires-Dist: httpx>=0.25.0
Requires-Dist: pydantic>=2.0.0
Requires-Dist: python-dotenv>=1.0.0
Requires-Dist: supabase>=2.0.0
Provides-Extra: postgres
Requires-Dist: psycopg[binary]>=3.0.0; extra == "postgres"
Provides-Extra: dev
Requires-Dist: pytest>=7.0.0; extra == "dev"
Requires-Dist: black>=23.0.0; extra == "dev"
Requires-Dist: flake8>=6.0.0; extra == "dev"
Requires-Dist: build>=0.10.0; extra == "dev"
Requires-Dist: twine>=4.0.0; extra == "dev"
Requires-Dist: toml>=0.10.2; extra == "dev"
Dynamic: license-file
